trytond/modules/health_orthanc/COPYING
trytond/modules/health_orthanc/README.rst
trytond/modules/health_orthanc/__init__.py
trytond/modules/health_orthanc/custom.js
trytond/modules/health_orthanc/data/data.xml
trytond/modules/health_orthanc/data/messages/messages.xml
trytond/modules/health_orthanc/health_orthanc.py
trytond/modules/health_orthanc/health_orthanc_configuration.py
trytond/modules/health_orthanc/health_orthanc_configuration_view.xml
trytond/modules/health_orthanc/health_orthanc_view.xml
trytond/modules/health_orthanc/icons/execute_icon.svg
trytond/modules/health_orthanc/icons/orthanc_logo.svg
trytond/modules/health_orthanc/locale/ar.po
trytond/modules/health_orthanc/locale/de.po
trytond/modules/health_orthanc/locale/el.po
trytond/modules/health_orthanc/locale/eo.po
trytond/modules/health_orthanc/locale/es.po
trytond/modules/health_orthanc/locale/fr.po
trytond/modules/health_orthanc/locale/health_orthanc.pot
trytond/modules/health_orthanc/locale/it_IT.po
trytond/modules/health_orthanc/locale/ja_JP.po
trytond/modules/health_orthanc/locale/ka.po
trytond/modules/health_orthanc/locale/lo.po
trytond/modules/health_orthanc/locale/pt_BR.po
trytond/modules/health_orthanc/locale/sv.po
trytond/modules/health_orthanc/locale/tr.po
trytond/modules/health_orthanc/locale/uk.po
trytond/modules/health_orthanc/locale/zh_CN.po
trytond/modules/health_orthanc/pyproject.toml
trytond/modules/health_orthanc/security/access_rights.xml
trytond/modules/health_orthanc/tests/__init__.py
trytond/modules/health_orthanc/tests/test_health_orthanc.py
trytond/modules/health_orthanc/tryton.cfg
trytond/modules/health_orthanc/view/add_orthanc_server_init_data.xml
trytond/modules/health_orthanc/view/full_synchronize_start_form.xml
trytond/modules/health_orthanc/view/get_new_studies_start_form.xml
trytond/modules/health_orthanc/view/imaging_form.xml
trytond/modules/health_orthanc/view/imaging_orthanc_patient_form.xml
trytond/modules/health_orthanc/view/imaging_orthanc_patient_tree.xml
gnuhealth_orthanc-5.0.2.dist-info/METADATA
gnuhealth_orthanc-5.0.2.dist-info/WHEEL
gnuhealth_orthanc-5.0.2.dist-info/licenses/COPYING
gnuhealth_orthanc-5.0.2.dist-info/RECORD
